teachable_machine.py
teachable_machine-1.2.1.dist-info/LICENSE
teachable_machine-1.2.1.dist-info/METADATA
teachable_machine-1.2.1.dist-info/WHEEL
teachable_machine-1.2.1.dist-info/top_level.txt
teachable_machine-1.2.1.dist-info/RECORD
