Metadata-Version: 2.1
Name: teachable-machine
Version: 1.2.1
Summary: A Python package designed to simplify the integration of exported models from Google's Teachable Machine platform into various environments.     This tool was specifically crafted to work seamlessly with Teachable Machine, making it easier to implement and use your trained models.
Home-page: https://github.com/MeqdadDev/teachable-machine
Author: Meqdad Dev
Author-email: meqdad.darweesh@gmail.com
License: UNKNOWN
Platform: UNKNOWN
Classifier: Programming Language :: Python :: 3
Classifier: Programming Language :: Python :: 3.7
Classifier: Programming Language :: Python :: 3.8
Classifier: Programming Language :: Python :: 3.9
Classifier: Programming Language :: Python :: 3.10
Classifier: Programming Language :: Python :: 3.11
Classifier: Programming Language :: Python :: 3.12
Classifier: Programming Language :: Python :: 3.13
Classifier: Topic :: Scientific/Engineering :: Image Processing
Classifier: Topic :: Scientific/Engineering :: Image Recognition
Classifier: Topic :: Scientific/Engineering :: Information Analysis
Classifier: License :: OSI Approved :: MIT License
Classifier: Operating System :: OS Independent
Requires-Python: >=3.7
License-File: LICENSE
Requires-Dist: Pillow
Requires-Dist: numpy
Requires-Dist: tensorflow
